filetype/__init__.py
filetype/__main__.py
filetype/filetype.py
filetype/helpers.py
filetype/match.py
filetype/utils.py
filetype/types/__init__.py
filetype/types/application.py
filetype/types/archive.py
filetype/types/audio.py
filetype/types/base.py
filetype/types/font.py
filetype/types/image.py
filetype/types/isobmff.py
filetype/types/video.py
filetype-1.1.0.dist-info/LICENSE
filetype-1.1.0.dist-info/METADATA
filetype-1.1.0.dist-info/WHEEL
filetype-1.1.0.dist-info/entry_points.txt
filetype-1.1.0.dist-info/top_level.txt
filetype-1.1.0.dist-info/zip-safe
filetype-1.1.0.dist-info/RECORD
