Metadata-Version: 1.1
Name: filetype
Version: 1.1.0
Summary: Infer file type and MIME type of any file/buffer. No external dependencies.
Home-page: https://github.com/h2non/filetype.py
Author: Tomas Aparicio
Author-email: tomas@aparicio.me
License: MIT
Download-URL: https://github.com/h2non/filetype.py/tarball/master
Keywords: file libmagic magic infer numbers magicnumbers discovery mime type kind
Platform: any
Classifier: Development Status :: 5 - Production/Stable
Classifier: Environment :: Console
Classifier: Environment :: Web Environment
Classifier: Intended Audience :: Developers
Classifier: Intended Audience :: System Administrators
Classifier: License :: OSI Approved :: MIT License
Classifier: Operating System :: OS Independent
Classifier: Programming Language :: Python :: 3
Classifier: Programming Language :: Python :: 3.5
Classifier: Programming Language :: Python :: 3.6
Classifier: Programming Language :: Python :: 3.7
Classifier: Programming Language :: Python :: 3.8
Classifier: Programming Language :: Python :: 3.9
Classifier: Topic :: System
Classifier: Topic :: System :: Filesystems
Classifier: Topic :: Utilities
